{
	"format_version": "1.12.0",
	"minecraft:geometry": [
		{
			"description": {
				"identifier": "geometry.darkness_terror",
				"texture_width": 128,
				"texture_height": 128,
				"visible_bounds_width": 8,
				"visible_bounds_height": 6,
				"visible_bounds_offset": [
					0,
					2,
					0
				]
			},
			"bones": [
				{
					"name": "root",
					"pivot": [
						0,
						0,
						0
					]
				},
				{
					"name": "body",
					"parent": "root",
					"pivot": [
						0,
						21,
						0
					],
					"cubes": [
						{
							"origin": [
								-8,
								18,
								-4
							],
							"size": [
								16,
								16,
								9
							],
							"uv": [
								0,
								32
							]
						}
					]
				},
				{
					"name": "head",
					"parent": "body",
					"pivot": [
						0,
						34,
						0
					],
					"cubes": [
						{
							"origin": [
								-6,
								34.1,
								-1
							],
							"size": [
								12,
								12,
								6
							],
							"uv": [
								38,
								0
							]
						}
					],
					"locators": {
						"death_cry": [
							0,
							41,
							-3
						]
					}
				},
				{
					"name": "top_right",
					"parent": "head",
					"pivot": [
						0,
						40,
						4
					],
					"cubes": [
						{
							"origin": [
								0,
								40,
								-21
							],
							"size": [
								6,
								6,
								26
							],
							"pivot": [
								3,
								43,
								-8
							],
							"rotation": [
								0,
								0,
								90
							],
							"uv": [
								0,
								0
							]
						}
					]
				},
				{
					"name": "bottom_right",
					"parent": "head",
					"pivot": [
						0,
						40,
						4
					],
					"cubes": [
						{
							"origin": [
								0,
								34,
								-21
							],
							"size": [
								6,
								6,
								26
							],
							"pivot": [
								3,
								37,
								-8
							],
							"rotation": [
								0,
								0,
								-180
							],
							"uv": [
								0,
								0
							]
						}
					]
				},
				{
					"name": "bottom_left",
					"parent": "head",
					"pivot": [
						0,
						40,
						4
					],
					"cubes": [
						{
							"origin": [
								-6,
								34,
								-21
							],
							"size": [
								6,
								6,
								26
							],
							"pivot": [
								-3,
								37,
								-8
							],
							"rotation": [
								0,
								0,
								-90
							],
							"uv": [
								0,
								0
							]
						}
					]
				},
				{
					"name": "top_left",
					"parent": "head",
					"pivot": [
						0,
						40,
						4
					],
					"cubes": [
						{
							"origin": [
								-6,
								40,
								-21
							],
							"size": [
								6,
								6,
								26
							],
							"uv": [
								0,
								0
							]
						}
					]
				},
				{
					"name": "left_horn",
					"parent": "head",
					"pivot": [
						0,
						34,
						0
					],
					"cubes": [
						{
							"origin": [
								-13,
								40,
								-2
							],
							"size": [
								8,
								6,
								6
							],
							"inflate": -0.5,
							"pivot": [
								-10,
								42,
								1
							],
							"rotation": [
								0,
								0,
								12.5
							],
							"uv": [
								50,
								32
							]
						},
						{
							"origin": [
								-20,
								44,
								-2
							],
							"size": [
								8,
								6,
								6
							],
							"inflate": -0.5,
							"pivot": [
								-16,
								44,
								1
							],
							"rotation": [
								0,
								0,
								50
							],
							"uv": [
								50,
								32
							]
						},
						{
							"origin": [
								-18.5,
								47.6,
								-1.5
							],
							"size": [
								5,
								7,
								5
							],
							"inflate": -0.5,
							"pivot": [
								-16,
								51.5,
								1
							],
							"rotation": [
								0,
								0,
								-5
							],
							"uv": [
								16,
								57
							]
						}
					]
				},
				{
					"name": "right_horn",
					"parent": "head",
					"pivot": [
						13.17524,
						46.59658,
						1
					],
					"rotation": [
						0,
						180,
						0
					],
					"cubes": [
						{
							"origin": [
								13,
								40,
								-2
							],
							"size": [
								8,
								6,
								6
							],
							"inflate": -0.5,
							"pivot": [
								16,
								42,
								1
							],
							"rotation": [
								0,
								0,
								12.5
							],
							"uv": [
								50,
								32
							]
						},
						{
							"origin": [
								6,
								44,
								-2
							],
							"size": [
								8,
								6,
								6
							],
							"inflate": -0.5,
							"pivot": [
								10,
								44,
								1
							],
							"rotation": [
								0,
								0,
								50
							],
							"uv": [
								50,
								32
							]
						},
						{
							"origin": [
								7.5,
								47.6,
								-1.5
							],
							"size": [
								5,
								7,
								5
							],
							"inflate": -0.5,
							"pivot": [
								10,
								51.5,
								1
							],
							"rotation": [
								0,
								0,
								-5
							],
							"uv": [
								16,
								57
							]
						}
					]
				},
				{
					"name": "right_arm",
					"parent": "body",
					"pivot": [
						-13,
						34,
						1
					],
					"cubes": [
						{
							"origin": [
								-12,
								16,
								-1
							],
							"size": [
								4,
								18,
								4
							],
							"uv": [
								50,
								44
							]
						}
					]
				},
				{
					"name": "bone2",
					"parent": "right_arm",
					"pivot": [
						-10,
						19,
						1
					],
					"cubes": [
						{
							"origin": [
								-10.75639,
								5.08774,
								-8
							],
							"size": [
								0,
								2,
								3
							],
							"pivot": [
								-10,
								6.08774,
								-6.771
							],
							"rotation": [
								56.76396,
								62.03205,
								-43.25978
							],
							"uv": [
								16,
								0
							]
						},
						{
							"origin": [
								-11.75639,
								5.08774,
								-8
							],
							"size": [
								0,
								2,
								3
							],
							"pivot": [
								-10,
								6.08774,
								-6.771
							],
							"rotation": [
								56.76396,
								62.03205,
								-43.25978
							],
							"uv": [
								16,
								0
							]
						},
						{
							"origin": [
								-12.75639,
								5.08774,
								-8
							],
							"size": [
								0,
								2,
								3
							],
							"pivot": [
								-10,
								6.08774,
								-6.771
							],
							"rotation": [
								56.76396,
								62.03205,
								-43.25978
							],
							"uv": [
								16,
								0
							]
						},
						{
							"origin": [
								-12,
								6.26785,
								-3.71892
							],
							"size": [
								4,
								14,
								4
							],
							"pivot": [
								-10,
								13.26785,
								-1.71892
							],
							"rotation": [
								-25,
								0,
								0
							],
							"uv": [
								0,
								75
							]
						}
					]
				},
				{
					"name": "left_arm",
					"parent": "body",
					"pivot": [
						13,
						34,
						1
					],
					"cubes": [
						{
							"origin": [
								8,
								16,
								-1
							],
							"size": [
								4,
								18,
								4
							],
							"uv": [
								0,
								0
							]
						}
					]
				},
				{
					"name": "bone",
					"parent": "left_arm",
					"pivot": [
						10,
						19,
						1
					],
					"cubes": [
						{
							"origin": [
								9.94984,
								5.03037,
								-7.8
							],
							"size": [
								0,
								2,
								3
							],
							"pivot": [
								10.94984,
								6.03037,
								-6.32378
							],
							"rotation": [
								-7.92602,
								66.96296,
								-89.5063
							],
							"uv": [
								16,
								2
							]
						},
						{
							"origin": [
								10.94984,
								5.03037,
								-7.8
							],
							"size": [
								0,
								2,
								3
							],
							"pivot": [
								10.94984,
								6.03037,
								-6.32378
							],
							"rotation": [
								-7.92602,
								66.96296,
								-89.5063
							],
							"uv": [
								16,
								2
							]
						},
						{
							"origin": [
								11.94984,
								5.03037,
								-7.8
							],
							"size": [
								0,
								2,
								3
							],
							"pivot": [
								10.94984,
								6.03037,
								-6.32378
							],
							"rotation": [
								-7.92602,
								66.96296,
								-89.5063
							],
							"uv": [
								16,
								2
							]
						},
						{
							"origin": [
								8,
								5,
								-4
							],
							"size": [
								4,
								14,
								4
							],
							"pivot": [
								-10,
								12,
								1
							],
							"rotation": [
								-25,
								0,
								0
							],
							"uv": [
								0,
								57
							]
						}
					]
				},
				{
					"name": "right_leg",
					"parent": "root",
					"pivot": [
						-4,
						18.5,
						0
					],
					"rotation": [
						-10,
						0,
						0
					],
					"cubes": [
						{
							"origin": [
								-6,
								8,
								-2
							],
							"size": [
								4,
								10,
								4
							],
							"uv": [
								64,
								18
							]
						},
						{
							"origin": [
								-6,
								0.5,
								-2
							],
							"size": [
								4,
								8,
								4
							],
							"pivot": [
								4,
								9,
								0
							],
							"rotation": [
								17.5,
								0,
								0
							],
							"uv": [
								52,
								68
							]
						},
						{
							"origin": [
								-6,
								-0.5,
								-3
							],
							"size": [
								4,
								2,
								7
							],
							"pivot": [
								4,
								0.5,
								0
							],
							"rotation": [
								10,
								0,
								0
							],
							"uv": [
								59,
								59
							]
						},
						{
							"origin": [
								-5,
								-1.5,
								-5
							],
							"size": [
								0,
								2,
								3
							],
							"uv": [
								16,
								0
							]
						},
						{
							"origin": [
								-4,
								-1.5,
								-5
							],
							"size": [
								0,
								2,
								3
							],
							"uv": [
								16,
								0
							]
						},
						{
							"origin": [
								-3,
								-1.5,
								-5
							],
							"size": [
								0,
								2,
								3
							],
							"uv": [
								16,
								0
							]
						},
						{
							"origin": [
								-3,
								0.5,
								3
							],
							"size": [
								3,
								2,
								0
							],
							"pivot": [
								1.5,
								1.5,
								3
							],
							"rotation": [
								10.98238,
								14.3042,
								-4.7979
							],
							"uv": [
								16,
								7
							]
						}
					]
				},
				{
					"name": "left_leg",
					"parent": "root",
					"pivot": [
						4,
						18.5,
						0
					],
					"rotation": [
						-10,
						0,
						0
					],
					"cubes": [
						{
							"origin": [
								2,
								8,
								-2
							],
							"size": [
								4,
								10,
								4
							],
							"uv": [
								36,
								62
							]
						},
						{
							"origin": [
								2,
								0.5,
								-2
							],
							"size": [
								4,
								8,
								4
							],
							"pivot": [
								4,
								9,
								0
							],
							"rotation": [
								17.5,
								0,
								0
							],
							"uv": [
								66,
								44
							]
						},
						{
							"origin": [
								5,
								-1.5,
								-5
							],
							"size": [
								0,
								2,
								3
							],
							"uv": [
								16,
								0
							]
						},
						{
							"origin": [
								0,
								0,
								3
							],
							"size": [
								3,
								2,
								0
							],
							"pivot": [
								1.5,
								1.5,
								3
							],
							"rotation": [
								10.98238,
								-14.3042,
								4.79794
							],
							"uv": [
								12,
								0
							]
						},
						{
							"origin": [
								3,
								-1.5,
								-5
							],
							"size": [
								0,
								2,
								3
							],
							"uv": [
								16,
								0
							]
						},
						{
							"origin": [
								4,
								-1.5,
								-5
							],
							"size": [
								0,
								2,
								3
							],
							"uv": [
								16,
								0
							]
						},
						{
							"origin": [
								2,
								-0.5,
								-3
							],
							"size": [
								4,
								2,
								7
							],
							"pivot": [
								4,
								0.5,
								0
							],
							"rotation": [
								10,
								0,
								0
							],
							"uv": [
								59,
								59
							]
						}
					]
				}
			]
		}
	]
}